{
    "annotations": [
        {
            "area": null,
            "bbox": [
                485,
                111,
                72,
                73
            ],
            "category_id": 1,
            "id": 0,
            "image_id": 0,
            "iscrowd": 0,
            "segmentation": [
                [
                    485,
                    111,
                    557,
                    184
                ]
            ]
        },
        {
            "area": null,
            "bbox": [
                605,
                113,
                74,
                76
            ],
            "category_id": 1,
            "id": 1,
            "image_id": 0,
            "iscrowd": 0,
            "segmentation": [
                [
                    605,
                    113,
                    679,
                    189
                ]
            ]
        },
        {
            "area": null,
            "bbox": [
                608,
                317,
                86,
                90
            ],
            "category_id": 1,
            "id": 2,
            "image_id": 0,
            "iscrowd": 0,
            "segmentation": [
                [
                    608,
                    317,
                    694,
                    407
                ]
            ]
        },
        {
            "area": null,
            "bbox": [
                607,
                452,
                86,
                90
            ],
            "category_id": 1,
            "id": 3,
            "image_id": 0,
            "iscrowd": 0,
            "segmentation": [
                [
                    607,
                    452,
                    693,
                    542
                ]
            ]
        },
        {
            "area": null,
            "bbox": [
                464,
                318,
                80,
                85
            ],
            "category_id": 1,
            "id": 4,
            "image_id": 0,
            "iscrowd": 0,
            "segmentation": [
                [
                    464,
                    318,
                    544,
                    403
                ]
            ]
        },
        {
            "area": null,
            "bbox": [
                608,
                206,
                80,
                85
            ],
            "category_id": 1,
            "id": 5,
            "image_id": 0,
            "iscrowd": 0,
            "segmentation": [
                [
                    608,
                    206,
                    688,
                    291
                ]
            ]
        },
        {
            "area": null,
            "bbox": [
                472,
                200,
                80,
                85
            ],
            "category_id": 1,
            "id": 6,
            "image_id": 0,
            "iscrowd": 0,
            "segmentation": [
                [
                    472,
                    200,
                    552,
                    285
                ]
            ]
        },
        {
            "area": null,
            "bbox": [
                484,
                409,
                91,
                95
            ],
            "category_id": 2,
            "id": 7,
            "image_id": 0,
            "iscrowd": 0,
            "segmentation": [
                [
                    484,
                    409,
                    575,
                    504
                ]
            ]
        }
    ],
    "categories": [
        {
            "id": 1,
            "name": "success",
            "supercategory": "vial"
        },
        {
            "id": 2,
            "name": "fail",
            "supercategory": "vial"
        }
    ],
    "images": [
        {
            "coco_url": "",
            "date_captured": "2021-07-27 11:47:46.285659",
            "file_name": "Empty_raw_01508.jpg",
            "flickr_url": "",
            "height": 720,
            "id": "01508",
            "license": 1,
            "width": 1280
        }
    ],
    "info": {
        "contributor": "KIST CSRC",
        "description": "Vial Positioning Dataset",
        "url": "https://github.com/KIST-CSRC/DenseSSD",
        "version": "0.1.0",
        "year": 2022
    },
    "licenses": [
        {
            "id": 1,
            "name": "Attribution-NonCommercial-ShareAlike License",
            "url": "http://creativecommons.org/licenses/by-nc-sa/2.0/"
        }
    ]
}